Metadata-Version: 1.0
Name: gotovrvex
Version: 0.1
Summary: The robot rides to the specified coordinates
Home-page: UNKNOWN
Author: UNKNOWN
Author-email: vl.archit@gmail.com
License: UNKNOWN
Platform: UNKNOWN
